{"BaseDirectory": "..\\..", "GPUName": "NVIDIA", "QASaveDirectory": "\\\\Cifs2\\ro_prphy$\\PBS\\GMC\\QABeams", "AENamesGmcSequence" : [{"AEGmcName": "nickAET"}, {"AEGmcName": "GMCAET"}], "PACSServerQuerySequence": [{"ServerName": "Main Server", "ServerAddress": "172.27.45.252", "ServerPort": "8177", "AESequence": [{ "AEName": "MIMDCMQUERY" }]}], "PACSServerSaveSequence": [{"ServerName": "Main Server", "ServerAddress": "172.27.45.252", "ServerPort": "4008", "AESequence": [{ "AEName": "MIM_SERVER" },{ "AEName": "MGH_PHY" }]}], "MIMMonitorLogFile": "..\\Libs.log"}